step/__init__.py
step/cli.py
step/external_cli.py
step/markdown.py
step/step.py
step/templates/cli.py.template
step/templates/command.py.template
step/templates/sub_steps.py.template
step-0.1.0.dist-info/METADATA
step-0.1.0.dist-info/WHEEL
step-0.1.0.dist-info/entry_points.txt
step-0.1.0.dist-info/RECORD
