Metadata-Version: 2.1
Name: step
Version: 0.1.0
Summary: The first step to automate things; from a Markdown into a CLI
License: MIT
Author: Ana Paula Gomes
Author-email: 1899950+anapaulagomes@users.noreply.github.com
Requires-Python: >=3.10,<4.0
Classifier: License :: OSI Approved :: MIT License
Classifier: Programming Language :: Python :: 3
Classifier: Programming Language :: Python :: 3.10
Classifier: Programming Language :: Python :: 3.11
Requires-Dist: mdformat (>=0.7.16,<0.8.0)
Requires-Dist: typer[all] (>=0.9.0,<0.10.0)
